setup_logging_for_me-0.1.0.dist-info/WHEEL
setup_logging_for_me-0.1.0.dist-info/RECORD
setup_logging_for_me-0.1.0.dist-info/top_level.txt
setup_logging_for_me-0.1.0.dist-info/metadata.json
setup_logging_for_me-0.1.0.dist-info/DESCRIPTION.rst
setup_logging_for_me-0.1.0.dist-info/METADATA
setup_logging_for_me/__init__.py
