Metadata-Version: 2.0
Name: setup-logging-for-me
Version: 0.1.0
Summary: I never remember how to do basic config
Home-page: https://github.com/jmansilla/setup_logging_for_me
Author: Javier Andrés Mansilla
Author-email: javimansilla@gmail.com
License: ISCL
Keywords: setup_logging_for_me
Platform: UNKNOWN
Classifier: Development Status :: 2 - Pre-Alpha
Classifier: Intended Audience :: Developers
Classifier: License :: OSI Approved :: ISC License (ISCL)
Classifier: Natural Language :: English
Classifier: Programming Language :: Python :: 2
Classifier: Programming Language :: Python :: 2.6
Classifier: Programming Language :: Python :: 2.7
Classifier: Programming Language :: Python :: 3
Classifier: Programming Language :: Python :: 3.3
Classifier: Programming Language :: Python :: 3.4
Classifier: Programming Language :: Python :: 3.5
